moodemoji/__init__.py
moodemoji/core.py
moodemoji-0.1.1.dist-info/METADATA
moodemoji-0.1.1.dist-info/WHEEL
moodemoji-0.1.1.dist-info/top_level.txt
moodemoji-0.1.1.dist-info/RECORD
