Metadata-Version: 2.4
Name: moodemoji
Version: 0.1.1
Summary: Map moods to emojis 😎
Author-email: Vedanta Barooah <barooah.io@gmail.com>
License: MIT
Project-URL: Homepage, https://github.com/vedanta/moodemoji
Requires-Python: >=3.7
